{
  "ticker": "NIFTYBEES.NS",
  "name": "Nippon Nifty BeES",
  "category": "ETF",
  "sector": "Broad Market",
  "updated_at": "2026-04-23T02:34:49.565642+05:30",
  "data_through": "2026-04-21",
  "regime": "High",
  "entropy": 0.0003,
  "stability": "Stable",
  "transition_risk": {
    "1d": 0.9903,
    "3d": 0.9903,
    "5d": 0.9932
  },
  "empirical_high_prob": 0.9754,
  "var_1pct": -0.049142,
  "var_5pct": -0.028286,
  "return_range": {
    "q10": -0.018475,
    "q50": 0.001185,
    "q90": 0.021819
  },
  "regime_stats": {
    "Low": {
      "mean": 0.000167,
      "std": 0.007942,
      "skew": -0.2456,
      "kurt": 0.9873,
      "var_1pct": -0.020671,
      "var_5pct": -0.013727,
      "q10": -0.009897,
      "q50": 0.000564,
      "q90": 0.009161,
      "count": 1733
    },
    "Medium": {
      "mean": 0.000751,
      "std": 0.007914,
      "skew": -0.0342,
      "kurt": 0.9701,
      "var_1pct": -0.019484,
      "var_5pct": -0.012379,
      "q10": -0.009266,
      "q50": 0.000894,
      "q90": 0.01003,
      "count": 1734
    },
    "High": {
      "mean": 0.001249,
      "std": 0.020515,
      "skew": 0.3126,
      "kurt": 16.2667,
      "var_1pct": -0.049142,
      "var_5pct": -0.028286,
      "q10": -0.018475,
      "q50": 0.001185,
      "q90": 0.021819,
      "count": 773
    }
  },
  "transition_matrix": {
    "Low": {
      "Low": 0.0,
      "Medium": 0.9977,
      "High": 0.0023
    },
    "Medium": {
      "Low": 0.9913,
      "Medium": 0.0,
      "High": 0.0087
    },
    "High": {
      "Low": 0.0181,
      "Medium": 0.0065,
      "High": 0.9754
    }
  }
}